{"type": "FeatureCollection", "features": [{"geometry": {"type": "Point", "coordinates": [-122.3545531, 47.6219664]}, "type": "Feature", "properties": {"neighborhood": "Lower Queen Anne", "encoding": "utf-8", "county": "King County", "city_long": "Seattle", "lng": -122.3545531, "quality": "street_address", "city": "Seattle", "confidence": 9, "state": "WA", "location": "305 Harrison Street, Seattle, WA 98109", "provider": "google", "housenumber": "305", "accuracy": "ROOFTOP", "status": "OK", "state_long": "Washington", "address": "305 Harrison Street, Seattle, WA 98109, USA", "lat": 47.6219664, "postal": "98109", "ok": true, "road_long": "Harrison Street", "country": "US", "country_long": "United States", "street": "Harrison St"}, "bbox": [-122.3559020802915, 47.6206174197085, -122.3532041197085, 47.6233153802915]}, {"geometry": {"type": "Point", "coordinates": [-122.319716, 47.613843]}, "type": "Feature", "properties": {"neighborhood": "First Hill", "encoding": "utf-8", "county": "King County", "city_long": "Seattle", "lng": -122.319716, "quality": "street_address", "city": "Seattle", "confidence": 9, "state": "WA", "location": "925 East Pike Street, Seattle, WA 98122", "provider": "google", "housenumber": "925", "accuracy": "ROOFTOP", "status": "OK", "state_long": "Washington", "address": "925 East Pike Street, Seattle, WA 98122, USA", "lat": 47.613843, "postal": "98122", "ok": true, "road_long": "East Pike Street", "country": "US", "country_long": "United States", "street": "E Pike St"}, "bbox": [-122.3210649802915, 47.61249401970849, -122.3183670197085, 47.61519198029149]}, {"geometry": {"type": "Point", "coordinates": [-122.3413842, 47.6117865]}, "type": "Feature", "properties": {"neighborhood": "Belltown", "encoding": "utf-8", "county": "King County", "city_long": "Seattle", "lng": -122.3413842, "quality": "street_address", "city": "Seattle", "confidence": 9, "state": "WA", "location": "1932 2nd Ave, Seattle, WA 98101", "provider": "google", "housenumber": "1932", "accuracy": "ROOFTOP", "status": "OK", "state_long": "Washington", "address": "1932 2nd Avenue, Seattle, WA 98101, USA", "lat": 47.6117865, "postal": "98101", "ok": true, "road_long": "2nd Avenue", "country": "US", "country_long": "United States", "street": "2nd Ave"}, "bbox": [-122.3427331802915, 47.6104375197085, -122.3400352197085, 47.6131354802915]}]}